secretset/__init__.py
secretset/main.py
secretset/map.py
secretset-0.1.1.dist-info/entry_points.txt
secretset-0.1.1.dist-info/LICENSE
secretset-0.1.1.dist-info/WHEEL
secretset-0.1.1.dist-info/METADATA
secretset-0.1.1.dist-info/RECORD
