Metadata-Version: 2.1
Name: secretset
Version: 0.1.1
Summary: Command line interface to anonymize data.
License: MIT
Author: Chris Pryer
Author-email: cnpryer@gmail.com
Requires-Python: >=3.10,<4.0
Classifier: License :: OSI Approved :: MIT License
Classifier: Programming Language :: Python :: 3
Classifier: Programming Language :: Python :: 3.10
Requires-Dist: click (>=8.1.3,<9.0.0)
Requires-Dist: openpyxl (>=3.0.10,<4.0.0)
Requires-Dist: pandas (>=1.4.3,<2.0.0)
